odoo/addons/prometheus_exporter_coopdevs/LICENSE
odoo/addons/prometheus_exporter_coopdevs/README.rst
odoo/addons/prometheus_exporter_coopdevs/__init__.py
odoo/addons/prometheus_exporter_coopdevs/__manifest__.py
odoo/addons/prometheus_exporter_coopdevs/data/ir_metric.xml
odoo/addons/prometheus_exporter_coopdevs/models/__init__.py
odoo/addons/prometheus_exporter_coopdevs/models/ir_metric.py
odoo_addon_prometheus_exporter_coopdevs-16.0.1.0.0.dist-info/METADATA
odoo_addon_prometheus_exporter_coopdevs-16.0.1.0.0.dist-info/WHEEL
odoo_addon_prometheus_exporter_coopdevs-16.0.1.0.0.dist-info/top_level.txt
odoo_addon_prometheus_exporter_coopdevs-16.0.1.0.0.dist-info/RECORD
