Metadata-Version: 2.1
Name: odoo-addon-prometheus-exporter-coopdevs
Version: 16.0.1.0.0
Summary: Monitor Odoo metrics with Prometheus.
Home-page: https://coopdevs.coop
Author: Coopdevs Treball SCCL
License: AGPL-3
Platform: UNKNOWN
Classifier: Programming Language :: Python
Classifier: Framework :: Odoo
Classifier: Framework :: Odoo :: 16.0
Classifier: License :: OSI Approved :: GNU Affero General Public License v3
Requires-Python: >=3.10
Requires-Dist: odoo-addon-prometheus-exporter (<16.1dev,>=16.0dev)
Requires-Dist: odoo (<16.1dev,>=16.0a)
